MANIFEST.in
README.md
setup.cfg
setup.py
pylint_beergarden/__init__.py
pylint_beergarden/checker.py
pylint_beergarden/plugin.py
pylint_beergarden.egg-info/PKG-INFO
pylint_beergarden.egg-info/SOURCES.txt
pylint_beergarden.egg-info/dependency_links.txt
pylint_beergarden.egg-info/requires.txt
pylint_beergarden.egg-info/top_level.txt